{
  "class_name": "Изобретатель",
  "hit_dice": 8,
  "proficient": [
    "constitution",
    "intelligence"
  ],
  "skills": [
    "perception",
    "history",
    "sleight_of_hand",
    "arcana",
    "medicine",
    "nature",
    "investigation."
  ],
  "using": {
    "доспехи": [
      "Лёгкие доспехи",
      "средние доспехи",
      "щиты"
    ],
    "оружие": [
      "Простое оружие"
    ],
    "инструменты": [
      "Воровские инструменты",
      "инструменты ремонтника",
      "а также один тип инструментов ремесленника на ваш выбор"
    ]
  },
  "equipment": [
    "два простых оружия на ваш выбор",
    "лёгкий арбалет и 20 болтов",
    [
      "проклёпанная кожа",
      "чешуйчатый доспех"
    ],
    "воровские инструменты и набор исследователя подземелий"
  ],
  "base_spell_mod": "intelligence",
  "abilities": {
    "1": {
      "": ""
    }
  }
}